odoo/addons/fastapi_auth_odoo_api_key/README.rst
odoo/addons/fastapi_auth_odoo_api_key/__init__.py
odoo/addons/fastapi_auth_odoo_api_key/__manifest__.py
odoo/addons/fastapi_auth_odoo_api_key/dependencies.py
odoo/addons/fastapi_auth_odoo_api_key/i18n/es.po
odoo/addons/fastapi_auth_odoo_api_key/models/__init__.py
odoo/addons/fastapi_auth_odoo_api_key/models/fastapi_endpoint.py
odoo/addons/fastapi_auth_odoo_api_key/models/res_users_apikeys_description.py
odoo/addons/fastapi_auth_odoo_api_key/readme/CONTRIBUTORS.md
odoo/addons/fastapi_auth_odoo_api_key/readme/DESCRIPTION.md
odoo/addons/fastapi_auth_odoo_api_key/readme/ROADMAP.md
odoo/addons/fastapi_auth_odoo_api_key/readme/USAGE.md
odoo/addons/fastapi_auth_odoo_api_key/static/description/icon.png
odoo/addons/fastapi_auth_odoo_api_key/static/description/index.html
odoo/addons/fastapi_auth_odoo_api_key/tests/__init__.py
odoo/addons/fastapi_auth_odoo_api_key/tests/test_auth.py
odoo/addons/fastapi_auth_odoo_api_key/views/fastapi_endpoint.xml
odoo_addon_fastapi_auth_odoo_api_key-17.0.1.1.0.dist-info/METADATA
odoo_addon_fastapi_auth_odoo_api_key-17.0.1.1.0.dist-info/WHEEL
odoo_addon_fastapi_auth_odoo_api_key-17.0.1.1.0.dist-info/top_level.txt
odoo_addon_fastapi_auth_odoo_api_key-17.0.1.1.0.dist-info/RECORD
