Metadata-Version: 2.1
Name: odoo-addon-fastapi_auth_odoo_api_key
Version: 17.0.1.1.0
Requires-Python: >=3.10
Requires-Dist: odoo-addon-apikey_scope_editable>=17.0dev,<17.1dev
Requires-Dist: odoo-addon-fastapi>=17.0dev,<17.1dev
Requires-Dist: odoo>=17.0a,<17.1dev
Summary: Auhentication for FastApi using Odoo's built in apikeys
Home-page: https://github.com/sygel-technology/sy-rest-framework
License: AGPL-3
Author: Sygel, Odoo Community Association (OCA)
Author-email: support@odoo-community.org
Classifier: Programming Language :: Python
Classifier: Framework :: Odoo
Classifier: Framework :: Odoo :: 17.0
Classifier: License :: OSI Approved :: GNU Affero General Public License v3
